<?xml version="1.0" encoding="UTF-8" standalone="no" ?><osm generator="OpenStreetMap server" version="0.6"><node id="70001" lat="39.7296752930" lon="116.1604537964"/><node id="70002" lat="39.7296829224" lon="116.1607589722"><tag k="highway" v="traffic_signals"/></node><node id="70003" lat="39.7296943665" lon="116.1615676880"/><node id="70004" lat="39.7296905518" lon="116.1627273560"/><node id="70005" lat="39.7296829224" lon="116.1642379761"/><node id="70006" lat="39.7296829224" lon="116.1652374268"/><node id="70007" lat="39.7297515869" lon="116.1664199829"><tag k="highway" v="traffic_signals"/></node><way id="70000"><nd ref="70001"/><nd ref="70002"/><nd ref="70003"/><nd ref="70004"/><nd ref="70005"/><nd ref="70006"/><nd ref="70007"/><tag k="oneway" v="yes"/></way></osm>