<?xml version="1.0" encoding="UTF-8"?>
<!--Generated by python, Author: Mengze.-->
<osm>
    <node id="110001" lat="38.75403103" lon="105.61178935">
        <tag k="highway" v="traffic_signals"/>
    </node>
    <node id="110002" lat="38.75403777" lon="105.61184641"/>
    <node id="110003" lat="38.75404860" lon="105.61190795"/>
    <node id="110004" lat="38.75405953" lon="105.61196289"/>
    <node id="110005" lat="38.75406527" lon="105.61200977"/>
    <node id="110006" lat="38.75407235" lon="105.61206427"/>
    <node id="110007" lat="38.75408061" lon="105.61211832"/>
    <node id="110008" lat="38.75408805" lon="105.61216772"/>
    <node id="110009" lat="38.75409867" lon="105.61222091"/>
    <node id="110010" lat="38.75410820" lon="105.61226798"/>
    <node id="110011" lat="38.75411758" lon="105.61232163"/>
    <node id="110012" lat="38.75412733" lon="105.61237023"/>
    <node id="110013" lat="38.75413698" lon="105.61243971"/>
    <node id="110014" lat="38.75414566" lon="105.61249649"/>
    <node id="110015" lat="38.75415418" lon="105.61254519"/>
    <node id="110016" lat="38.75416322" lon="105.61259686"/>
    <node id="110017" lat="38.75417278" lon="105.61265148"/>
    <node id="110018" lat="38.75418152" lon="105.61270147"/>
    <node id="110019" lat="38.75419131" lon="105.61275743"/>
    <node id="110020" lat="38.75420016" lon="105.61281513"/>
    <node id="110021" lat="38.75420807" lon="105.61286034"/>
    <node id="110022" lat="38.75421876" lon="105.61291422"/>
    <node id="110023" lat="38.75422813" lon="105.61296052"/>
    <node id="110024" lat="38.75423770" lon="105.61300821"/>
    <node id="110025" lat="38.75424817" lon="105.61305401"/>
    <node id="110026" lat="38.75425719" lon="105.61309858"/>
    <node id="110027" lat="38.75426542" lon="105.61313860"/>
    <node id="110028" lat="38.75427350" lon="105.61318486"/>
    <node id="110029" lat="38.75428066" lon="105.61323289"/>
    <node id="110030" lat="38.75428664" lon="105.61328114"/>
    <node id="110031" lat="38.75429338" lon="105.61333376"/>
    <node id="110032" lat="38.75430141" lon="105.61339371"/>
    <node id="110033" lat="38.75430905" lon="105.61344438"/>
    <node id="110034" lat="38.75431602" lon="105.61349819"/>
    <node id="110035" lat="38.75432326" lon="105.61353956"/>
    <node id="110036" lat="38.75433050" lon="105.61358087"/>
    <node id="110037" lat="38.75433644" lon="105.61361477"/>
    <node id="110038" lat="38.75434222" lon="105.61365479"/>
    <node id="110039" lat="38.75435410" lon="105.61370867"/>
    <node id="110040" lat="38.75436255" lon="105.61375668"/>
    <node id="110041" lat="38.75436920" lon="105.61380838"/>
    <node id="110042" lat="38.75437648" lon="105.61385665"/>
    <node id="110043" lat="38.75438517" lon="105.61390599"/>
    <node id="110044" lat="38.75439359" lon="105.61395381"/>
    <node id="110045" lat="38.75440069" lon="105.61399412"/>
    <node id="110046" lat="38.75440909" lon="105.61404187"/>
    <node id="110047" lat="38.75441450" lon="105.61407951"/>
    <node id="110048" lat="38.75442290" lon="105.61412718"/>
    <node id="110049" lat="38.75442945" lon="105.61416441"/>
    <node id="110050" lat="38.75443705" lon="105.61420756"/>
    <node id="110051" lat="38.75444528" lon="105.61424736"/>
    <node id="110052" lat="38.75445220" lon="105.61427970"/>
    <node id="110053" lat="38.75445881" lon="105.61433123"/>
    <node id="110054" lat="38.75446353" lon="105.61437907"/>
    <node id="110055" lat="38.75447089" lon="105.61442112"/>
    <node id="110056" lat="38.75447788" lon="105.61446801"/>
    <node id="110057" lat="38.75448293" lon="105.61451073"/>
    <node id="110058" lat="38.75448954" lon="105.61456190"/>
    <node id="110059" lat="38.75449783" lon="105.61461535"/>
    <node id="110060" lat="38.75450762" lon="105.61466367"/>
    <node id="110061" lat="38.75451716" lon="105.61471054"/>
    <node id="110062" lat="38.75452785" lon="105.61475707"/>
    <node id="110063" lat="38.75453660" lon="105.61479954"/>
    <node id="110064" lat="38.75454641" lon="105.61484794"/>
    <node id="110065" lat="38.75455356" lon="105.61490184"/>
    <node id="110066" lat="38.75455924" lon="105.61494062"/>
    <node id="110067" lat="38.75456534" lon="105.61498862"/>
    <node id="110068" lat="38.75457244" lon="105.61504268"/>
    <node id="110069" lat="38.75458092" lon="105.61509787"/>
    <node id="110070" lat="38.75458810" lon="105.61514559"/>
    <node id="110071" lat="38.75459489" lon="105.61519801"/>
    <node id="110072" lat="38.75460360" lon="105.61525446"/>
    <node id="110073" lat="38.75461267" lon="105.61530607"/>
    <node id="110074" lat="38.75462288" lon="105.61535729"/>
    <node id="110075" lat="38.75463329" lon="105.61540987"/>
    <node id="110076" lat="38.75464560" lon="105.61546643"/>
    <node id="110077" lat="38.75465443" lon="105.61551003"/>
    <node id="110078" lat="38.75466236" lon="105.61555535"/>
    <node id="110079" lat="38.75466976" lon="105.61559767"/>
    <node id="110080" lat="38.75467715" lon="105.61563993"/>
    <node id="110081" lat="38.75468618" lon="105.61568472"/>
    <node id="110082" lat="38.75469469" lon="105.61573293"/>
    <node id="110083" lat="38.75470271" lon="105.61577826"/>
    <node id="110084" lat="38.75471201" lon="105.61583088"/>
    <node id="110085" lat="38.75472016" lon="105.61588379"/>
    <node id="110086" lat="38.75472679" lon="105.61594165"/>
    <node id="110087" lat="38.75473417" lon="105.61599013"/>
    <node id="110088" lat="38.75474128" lon="105.61603713"/>
    <node id="110089" lat="38.75474827" lon="105.61609024"/>
    <node id="110090" lat="38.75475268" lon="105.61612874"/>
    <node id="90047" lat="38.75475875" lon="105.61616985">
        <tag k="highway" v="traffic_signals"/>
    </node>
    <way id="110000">
        <nd ref="110001"/>
        <nd ref="110002"/>
        <nd ref="110003"/>
        <nd ref="110004"/>
        <nd ref="110005"/>
        <nd ref="110006"/>
        <nd ref="110007"/>
        <nd ref="110008"/>
        <nd ref="110009"/>
        <nd ref="110010"/>
        <nd ref="110011"/>
        <nd ref="110012"/>
        <nd ref="110013"/>
        <nd ref="110014"/>
        <nd ref="110015"/>
        <nd ref="110016"/>
        <nd ref="110017"/>
        <nd ref="110018"/>
        <nd ref="110019"/>
        <nd ref="110020"/>
        <nd ref="110021"/>
        <nd ref="110022"/>
        <nd ref="110023"/>
        <nd ref="110024"/>
        <nd ref="110025"/>
        <nd ref="110026"/>
        <nd ref="110027"/>
        <nd ref="110028"/>
        <nd ref="110029"/>
        <nd ref="110030"/>
        <nd ref="110031"/>
        <nd ref="110032"/>
        <nd ref="110033"/>
        <nd ref="110034"/>
        <nd ref="110035"/>
        <nd ref="110036"/>
        <nd ref="110037"/>
        <nd ref="110038"/>
        <nd ref="110039"/>
        <nd ref="110040"/>
        <nd ref="110041"/>
        <nd ref="110042"/>
        <nd ref="110043"/>
        <nd ref="110044"/>
        <nd ref="110045"/>
        <nd ref="110046"/>
        <nd ref="110047"/>
        <nd ref="110048"/>
        <nd ref="110049"/>
        <nd ref="110050"/>
        <nd ref="110051"/>
        <nd ref="110052"/>
        <nd ref="110053"/>
        <nd ref="110054"/>
        <nd ref="110055"/>
        <nd ref="110056"/>
        <nd ref="110057"/>
        <nd ref="110058"/>
        <nd ref="110059"/>
        <nd ref="110060"/>
        <nd ref="110061"/>
        <nd ref="110062"/>
        <nd ref="110063"/>
        <nd ref="110064"/>
        <nd ref="110065"/>
        <nd ref="110066"/>
        <nd ref="110067"/>
        <nd ref="110068"/>
        <nd ref="110069"/>
        <nd ref="110070"/>
        <nd ref="110071"/>
        <nd ref="110072"/>
        <nd ref="110073"/>
        <nd ref="110074"/>
        <nd ref="110075"/>
        <nd ref="110076"/>
        <nd ref="110077"/>
        <nd ref="110078"/>
        <nd ref="110079"/>
        <nd ref="110080"/>
        <nd ref="110081"/>
        <nd ref="110082"/>
        <nd ref="110083"/>
        <nd ref="110084"/>
        <nd ref="110085"/>
        <nd ref="110086"/>
        <nd ref="110087"/>
        <nd ref="110088"/>
        <nd ref="110089"/>
        <nd ref="110090"/>
        <nd ref="90047"/>
        <tag k="name:en" v="double way"/>
    </way>
</osm>
