<?xml version="1.0" encoding="UTF-8"?>
<!--Generated by python, Author: Mengze.-->
<osm>
    <node id="200042" lat="38.76549200" lon="105.62263287">
        <tag k="highway" v="traffic_signals"/>
    </node>
    <node id="210002" lat="38.76548924" lon="105.62268690"/>
    <node id="210003" lat="38.76548414" lon="105.62274874"/>
    <node id="210004" lat="38.76547929" lon="105.62281255"/>
    <node id="210005" lat="38.76548018" lon="105.62288840"/>
    <node id="210006" lat="38.76548955" lon="105.62297294"/>
    <node id="210007" lat="38.76548777" lon="105.62304166"/>
    <node id="210008" lat="38.76548833" lon="105.62313127">
        <tag k="highway" v="traffic_signals"/>
    </node>
    <way id="210000">
        <nd ref="200042"/>
        <nd ref="210002"/>
        <nd ref="210003"/>
        <nd ref="210004"/>
        <nd ref="210005"/>
        <nd ref="210006"/>
        <nd ref="210007"/>
        <nd ref="210008"/>
        <tag k="name:en" v="double way"/>
    </way>
</osm>
