<?xml version="1.0" encoding="UTF-8"?>
<!--Generated by python, Author: Mengze.-->
<osm>
    <node id="110001" lat="38.75403103" lon="105.61178935">
        <tag k="highway" v="traffic_signals"/>
    </node>
    <node id="380002" lat="38.75399610" lon="105.61179747"/>
    <node id="380003" lat="38.75394974" lon="105.61181521"/>
    <node id="380004" lat="38.75390680" lon="105.61183001"/>
    <node id="380005" lat="38.75387015" lon="105.61184379"/>
    <node id="380006" lat="38.75382851" lon="105.61185515"/>
    <node id="380007" lat="38.75379023" lon="105.61187123"/>
    <node id="380008" lat="38.75374760" lon="105.61188618"/>
    <node id="380009" lat="38.75371113" lon="105.61190153"/>
    <node id="380010" lat="38.75367679" lon="105.61191164"/>
    <node id="380011" lat="38.75362982" lon="105.61192478"/>
    <node id="380012" lat="38.75357568" lon="105.61194138"/>
    <node id="380013" lat="38.75353962" lon="105.61195501"/>
    <node id="380014" lat="38.75349910" lon="105.61196745"/>
    <node id="380015" lat="38.75345514" lon="105.61198242"/>
    <node id="380016" lat="38.75342086" lon="105.61199409"/>
    <node id="380017" lat="38.75338177" lon="105.61200740"/>
    <node id="380018" lat="38.75333605" lon="105.61202297"/>
    <node id="380019" lat="38.75329236" lon="105.61204297"/>
    <node id="380020" lat="38.75325770" lon="105.61205979"/>
    <node id="380021" lat="38.75321108" lon="105.61207680"/>
    <node id="380022" lat="38.75316292" lon="105.61209553"/>
    <node id="380023" lat="38.75312748" lon="105.61211114"/>
    <node id="380024" lat="38.75308739" lon="105.61212461"/>
    <node id="380025" lat="38.75305018" lon="105.61213830"/>
    <node id="380026" lat="38.75299698" lon="105.61215650"/>
    <node id="380027" lat="38.75295790" lon="105.61217378"/>
    <node id="380028" lat="38.75291789" lon="105.61218860"/>
    <node id="380029" lat="38.75287780" lon="105.61220476"/>
    <node id="380030" lat="38.75284371" lon="105.61221753"/>
    <node id="380031" lat="38.75280480" lon="105.61223190"/>
    <node id="380032" lat="38.75276613" lon="105.61224357"/>
    <node id="380033" lat="38.75271992" lon="105.61225780"/>
    <node id="380034" lat="38.75266997" lon="105.61227458"/>
    <node id="380035" lat="38.75262594" lon="105.61228812"/>
    <node id="380036" lat="38.75258505" lon="105.61230187"/>
    <node id="380037" lat="38.75253635" lon="105.61232190"/>
    <node id="380038" lat="38.75249025" lon="105.61233856"/>
    <node id="380039" lat="38.75242405" lon="105.61236274"/>
    <node id="380040" lat="38.75238668" lon="105.61237669"/>
    <node id="380041" lat="38.75234174" lon="105.61239182"/>
    <node id="380042" lat="38.75229818" lon="105.61240651"/>
    <node id="380043" lat="38.75225767" lon="105.61242018"/>
    <node id="380044" lat="38.75221710" lon="105.61243517"/>
    <node id="380045" lat="38.75218352" lon="105.61244650"/>
    <node id="380046" lat="38.75213822" lon="105.61246180"/>
    <node id="380047" lat="38.75209086" lon="105.61247779"/>
    <node id="380048" lat="38.75205065" lon="105.61249262"/>
    <node id="380049" lat="38.75200903" lon="105.61250666"/>
    <node id="380050" lat="38.75195666" lon="105.61252445"/>
    <node id="380051" lat="38.75191962" lon="105.61253956"/>
    <node id="380052" lat="38.75187991" lon="105.61255425"/>
    <node id="380053" lat="38.75184267" lon="105.61256681"/>
    <node id="380054" lat="38.75179749" lon="105.61258454"/>
    <node id="380055" lat="38.75175520" lon="105.61260123"/>
    <node id="380056" lat="38.75171946" lon="105.61261567"/>
    <node id="380057" lat="38.75167998" lon="105.61263254"/>
    <node id="380058" lat="38.75163701" lon="105.61265170"/>
    <node id="380059" lat="38.75158835" lon="105.61267025"/>
    <node id="380060" lat="38.75154132" lon="105.61268585"/>
    <node id="380061" lat="38.75150143" lon="105.61269559"/>
    <node id="380062" lat="38.75146423" lon="105.61270564"/>
    <node id="380063" lat="38.75144302" lon="105.61270949">
        <tag k="highway" v="traffic_signals"/>
    </node>
    <way id="380000">
        <nd ref="110001"/>
        <nd ref="380002"/>
        <nd ref="380003"/>
        <nd ref="380004"/>
        <nd ref="380005"/>
        <nd ref="380006"/>
        <nd ref="380007"/>
        <nd ref="380008"/>
        <nd ref="380009"/>
        <nd ref="380010"/>
        <nd ref="380011"/>
        <nd ref="380012"/>
        <nd ref="380013"/>
        <nd ref="380014"/>
        <nd ref="380015"/>
        <nd ref="380016"/>
        <nd ref="380017"/>
        <nd ref="380018"/>
        <nd ref="380019"/>
        <nd ref="380020"/>
        <nd ref="380021"/>
        <nd ref="380022"/>
        <nd ref="380023"/>
        <nd ref="380024"/>
        <nd ref="380025"/>
        <nd ref="380026"/>
        <nd ref="380027"/>
        <nd ref="380028"/>
        <nd ref="380029"/>
        <nd ref="380030"/>
        <nd ref="380031"/>
        <nd ref="380032"/>
        <nd ref="380033"/>
        <nd ref="380034"/>
        <nd ref="380035"/>
        <nd ref="380036"/>
        <nd ref="380037"/>
        <nd ref="380038"/>
        <nd ref="380039"/>
        <nd ref="380040"/>
        <nd ref="380041"/>
        <nd ref="380042"/>
        <nd ref="380043"/>
        <nd ref="380044"/>
        <nd ref="380045"/>
        <nd ref="380046"/>
        <nd ref="380047"/>
        <nd ref="380048"/>
        <nd ref="380049"/>
        <nd ref="380050"/>
        <nd ref="380051"/>
        <nd ref="380052"/>
        <nd ref="380053"/>
        <nd ref="380054"/>
        <nd ref="380055"/>
        <nd ref="380056"/>
        <nd ref="380057"/>
        <nd ref="380058"/>
        <nd ref="380059"/>
        <nd ref="380060"/>
        <nd ref="380061"/>
        <nd ref="380062"/>
        <nd ref="380063"/>
        <tag k="name:en" v="double way"/>
    </way>
</osm>
