<?xml version="1.0" encoding="UTF-8"?>
<!--Generated by python, Author: Mengze.-->
<osm>
    <node id="110001" lat="38.76109783" lon="105.62099034" vel="5" wall="0">
        <tag k="highway" v="traffic_signals"/>
    </node>
    <node id="110002" lat="38.76105446" lon="105.62098996" vel="5" wall="0"/>
    <node id="110003" lat="38.76100808" lon="105.62099274" vel="5" wall="0"/>
    <node id="110004" lat="38.76095251" lon="105.62099990" vel="5" wall="0"/>
    <node id="110005" lat="38.76090230" lon="105.62100398" vel="5" wall="0"/>
    <node id="110006" lat="38.76085551" lon="105.62101180" vel="5" wall="0"/>
    <node id="110007" lat="38.76081904" lon="105.62101439" vel="5" wall="0"/>
    <node id="110008" lat="38.76076402" lon="105.62102320" vel="5" wall="0"/>
    <node id="90012" lat="38.76072667" lon="105.62102632" vel="5" wall="0">
        <tag k="highway" v="traffic_signals"/>
    </node>
    <way id="110000">
        <nd ref="110001"/>
        <nd ref="110002"/>
        <nd ref="110003"/>
        <nd ref="110004"/>
        <nd ref="110005"/>
        <nd ref="110006"/>
        <nd ref="110007"/>
        <nd ref="110008"/>
        <nd ref="90012"/>
        <tag k="name:en" v="double way"/>
    </way>
</osm>
