<?xml version="1.0" encoding="UTF-8"?>
<!--Generated by python, Author: Mengze.-->
<osm>
    <node ditch="0" id="450007" lat="28.11070359" lon="112.86303507" vel="5" wall="0">
        <tag k="highway" v="traffic_signals"/>
    </node>
    <node ditch="0" id="830002" lat="28.11078769" lon="112.86307919" vel="5" wall="0"/>
    <node ditch="0" id="830003" lat="28.11083965" lon="112.86310903" vel="5" wall="0"/>
    <node ditch="0" id="830004" lat="28.11090197" lon="112.86314052" vel="5" wall="0"/>
    <node ditch="0" id="830005" lat="28.11096909" lon="112.86317584" vel="5" wall="0"/>
    <node ditch="0" id="830006" lat="28.11103502" lon="112.86322015" vel="5" wall="0"/>
    <node ditch="0" id="830007" lat="28.11110796" lon="112.86327151" vel="5" wall="0"/>
    <node ditch="0" id="830008" lat="28.11116163" lon="112.86330751" vel="5" wall="0"/>
    <node ditch="0" id="830009" lat="28.11122827" lon="112.86334557" vel="5" wall="0"/>
    <node ditch="0" id="830010" lat="28.11127529" lon="112.86337136" vel="5" wall="0"/>
    <node ditch="0" id="830011" lat="28.11133411" lon="112.86340815" vel="5" wall="0"/>
    <node ditch="0" id="830012" lat="28.11139030" lon="112.86344452" vel="5" wall="0"/>
    <node ditch="0" id="830013" lat="28.11148589" lon="112.86351208" vel="5" wall="0"/>
    <node ditch="0" id="830014" lat="28.11155895" lon="112.86356340" vel="5" wall="0"/>
    <node ditch="0" id="830015" lat="28.11163528" lon="112.86360913" vel="5" wall="0"/>
    <node ditch="0" id="830016" lat="28.11170163" lon="112.86365053" vel="5" wall="0"/>
    <node ditch="0" id="830017" lat="28.11177250" lon="112.86368668" vel="5" wall="0"/>
    <node ditch="0" id="830018" lat="28.11182420" lon="112.86371653" vel="5" wall="0"/>
    <node ditch="0" id="830019" lat="28.11187854" lon="112.86374717" vel="5" wall="0"/>
    <node ditch="0" id="830020" lat="28.11194536" lon="112.86378040" vel="5" wall="0"/>
    <node ditch="0" id="830021" lat="28.11201626" lon="112.86381117" vel="5" wall="0"/>
    <node ditch="0" id="830022" lat="28.11208430" lon="112.86384689" vel="5" wall="0"/>
    <node ditch="0" id="830023" lat="28.11214312" lon="112.86388166" vel="5" wall="0"/>
    <node ditch="0" id="830024" lat="28.11220157" lon="112.86391743" vel="5" wall="0"/>
    <node ditch="0" id="830025" lat="28.11225567" lon="112.86395459" vel="5" wall="0"/>
    <node ditch="0" id="830026" lat="28.11230953" lon="112.86399585" vel="5" wall="0"/>
    <node ditch="0" id="830027" lat="28.11236422" lon="112.86403932" vel="5" wall="0"/>
    <node ditch="0" id="830028" lat="28.11241860" lon="112.86408307" vel="5" wall="0"/>
    <node ditch="0" id="830029" lat="28.11247339" lon="112.86412607" vel="5" wall="0"/>
    <node ditch="0" id="830030" lat="28.11252844" lon="112.86416522" vel="5" wall="0"/>
    <node ditch="0" id="830031" lat="28.11258665" lon="112.86420173" vel="5" wall="0"/>
    <node ditch="0" id="830032" lat="28.11264476" lon="112.86423745" vel="5" wall="0"/>
    <node ditch="0" id="830033" lat="28.11270256" lon="112.86427398" vel="5" wall="0"/>
    <node ditch="0" id="830034" lat="28.11275964" lon="112.86431200" vel="5" wall="0"/>
    <node ditch="0" id="830035" lat="28.11282977" lon="112.86436200" vel="5" wall="0"/>
    <node ditch="0" id="830036" lat="28.11289850" lon="112.86441429" vel="5" wall="0"/>
    <node ditch="0" id="830037" lat="28.11297946" lon="112.86448061" vel="5" wall="0"/>
    <node ditch="0" id="830038" lat="28.11305809" lon="112.86454926" vel="5" wall="0"/>
    <node ditch="0" id="830039" lat="28.11312175" lon="112.86460884" vel="5" wall="0"/>
    <node ditch="0" id="830040" lat="28.11318410" lon="112.86466977" vel="5" wall="0"/>
    <node ditch="0" id="830041" lat="28.11324497" lon="112.86473251" vel="5" wall="0"/>
    <node ditch="0" id="830042" lat="28.11330286" lon="112.86479654" vel="5" wall="0"/>
    <node ditch="0" id="830043" lat="28.11334801" lon="112.86484947" vel="5" wall="0"/>
    <node ditch="0" id="830044" lat="28.11340749" lon="112.86491434" vel="5" wall="0"/>
    <node ditch="0" id="830045" lat="28.11346894" lon="112.86497650" vel="5" wall="0"/>
    <node ditch="0" id="830046" lat="28.11351778" lon="112.86502785" vel="5" wall="0"/>
    <node ditch="0" id="830047" lat="28.11356547" lon="112.86507995" vel="5" wall="0"/>
    <node ditch="0" id="830048" lat="28.11361261" lon="112.86513274" vel="5" wall="0"/>
    <node ditch="0" id="830049" lat="28.11365943" lon="112.86518534" vel="5" wall="0"/>
    <node ditch="0" id="830050" lat="28.11370600" lon="112.86523800" vel="5" wall="0"/>
    <node ditch="0" id="830051" lat="28.11376373" lon="112.86530216" vel="5" wall="0"/>
    <node ditch="0" id="830052" lat="28.11382612" lon="112.86536465" vel="5" wall="0"/>
    <node ditch="0" id="830053" lat="28.11387557" lon="112.86541505" vel="5" wall="0"/>
    <node ditch="0" id="830054" lat="28.11393741" lon="112.86547716" vel="5" wall="0"/>
    <node ditch="0" id="830055" lat="28.11400034" lon="112.86553813" vel="5" wall="0"/>
    <node ditch="0" id="830056" lat="28.11406346" lon="112.86559842" vel="5" wall="0"/>
    <node ditch="0" id="830057" lat="28.11413902" lon="112.86567097" vel="5" wall="0"/>
    <node ditch="0" id="830058" lat="28.11420213" lon="112.86573129" vel="5" wall="0"/>
    <node ditch="0" id="830059" lat="28.11426551" lon="112.86579139" vel="5" wall="0"/>
    <node ditch="0" id="830060" lat="28.11432925" lon="112.86585083" vel="5" wall="0"/>
    <node ditch="0" id="830061" lat="28.11439330" lon="112.86591059" vel="5" wall="0"/>
    <node ditch="0" id="830062" lat="28.11444487" lon="112.86595764" vel="5" wall="0"/>
    <node ditch="0" id="830063" lat="28.11449734" lon="112.86600383" vel="5" wall="0"/>
    <node ditch="0" id="830064" lat="28.11456175" lon="112.86606351" vel="5" wall="0"/>
    <node ditch="0" id="830065" lat="28.11462223" lon="112.86612120" vel="5" wall="0"/>
    <node ditch="0" id="830066" lat="28.11468956" lon="112.86617765" vel="5" wall="0"/>
    <node ditch="0" id="830067" lat="28.11475590" lon="112.86623224" vel="5" wall="0"/>
    <node ditch="0" id="830068" lat="28.11482309" lon="112.86628785" vel="5" wall="0"/>
    <node ditch="0" id="830069" lat="28.11488445" lon="112.86633870" vel="5" wall="0"/>
    <node ditch="0" id="830070" lat="28.11493845" lon="112.86638674" vel="5" wall="0"/>
    <node ditch="0" id="830071" lat="28.11498778" lon="112.86643658" vel="5" wall="0"/>
    <node ditch="0" id="830072" lat="28.11504723" lon="112.86650042" vel="5" wall="0"/>
    <node ditch="0" id="830073" lat="28.11508726" lon="112.86655650" vel="5" wall="0"/>
    <node ditch="0" id="530040" lat="28.11511796" lon="112.86660830" vel="5" wall="0">
        <tag k="highway" v="traffic_signals"/>
    </node>
    <way id="830000">
        <nd ref="450007"/>
        <nd ref="830002"/>
        <nd ref="830003"/>
        <nd ref="830004"/>
        <nd ref="830005"/>
        <nd ref="830006"/>
        <nd ref="830007"/>
        <nd ref="830008"/>
        <nd ref="830009"/>
        <nd ref="830010"/>
        <nd ref="830011"/>
        <nd ref="830012"/>
        <nd ref="830013"/>
        <nd ref="830014"/>
        <nd ref="830015"/>
        <nd ref="830016"/>
        <nd ref="830017"/>
        <nd ref="830018"/>
        <nd ref="830019"/>
        <nd ref="830020"/>
        <nd ref="830021"/>
        <nd ref="830022"/>
        <nd ref="830023"/>
        <nd ref="830024"/>
        <nd ref="830025"/>
        <nd ref="830026"/>
        <nd ref="830027"/>
        <nd ref="830028"/>
        <nd ref="830029"/>
        <nd ref="830030"/>
        <nd ref="830031"/>
        <nd ref="830032"/>
        <nd ref="830033"/>
        <nd ref="830034"/>
        <nd ref="830035"/>
        <nd ref="830036"/>
        <nd ref="830037"/>
        <nd ref="830038"/>
        <nd ref="830039"/>
        <nd ref="830040"/>
        <nd ref="830041"/>
        <nd ref="830042"/>
        <nd ref="830043"/>
        <nd ref="830044"/>
        <nd ref="830045"/>
        <nd ref="830046"/>
        <nd ref="830047"/>
        <nd ref="830048"/>
        <nd ref="830049"/>
        <nd ref="830050"/>
        <nd ref="830051"/>
        <nd ref="830052"/>
        <nd ref="830053"/>
        <nd ref="830054"/>
        <nd ref="830055"/>
        <nd ref="830056"/>
        <nd ref="830057"/>
        <nd ref="830058"/>
        <nd ref="830059"/>
        <nd ref="830060"/>
        <nd ref="830061"/>
        <nd ref="830062"/>
        <nd ref="830063"/>
        <nd ref="830064"/>
        <nd ref="830065"/>
        <nd ref="830066"/>
        <nd ref="830067"/>
        <nd ref="830068"/>
        <nd ref="830069"/>
        <nd ref="830070"/>
        <nd ref="830071"/>
        <nd ref="830072"/>
        <nd ref="830073"/>
        <nd ref="530040"/>
        <tag k="name:en" v="double way"/>
    </way>
</osm>
