<?xml version="1.0" encoding="UTF-8"?>
<!--Generated by python, Author: Mengze.-->
<osm>
    <node concave_ob="0" dyn_ob="0" id="2490007" lat="40.16060186" lon="116.11489992" smoke="0" type="-1" vel="4.2" water="0">
        <tag k="highway" v="traffic_signals"/>
    </node>
    <node concave_ob="0" dyn_ob="0" id="2540001" lat="40.16055506" lon="116.11487071" smoke="0" type="-1" vel="4.2" water="0"/>
    <node concave_ob="0" dyn_ob="0" id="2540002" lat="40.16050325" lon="116.11482779" smoke="0" type="-1" vel="4.2" water="0"/>
    <node concave_ob="0" dyn_ob="0" id="2540003" lat="40.16044701" lon="116.11478302" smoke="0" type="-1" vel="8.4" water="0"/>
    <node concave_ob="0" dyn_ob="0" id="2540004" lat="40.16041411" lon="116.11473683" smoke="0" type="-1" vel="8.4" water="0"/>
    <node concave_ob="0" dyn_ob="0" id="2540005" lat="40.16037659" lon="116.11468396" smoke="0" type="-1" vel="8.4" water="0"/>
    <node concave_ob="0" dyn_ob="0" id="2540006" lat="40.16033501" lon="116.11463517" smoke="0" type="-1" vel="8.4" water="0"/>
    <node concave_ob="0" dyn_ob="0" id="2540007" lat="40.16029202" lon="116.11459528" smoke="0" type="-1" vel="4.2" water="0"/>
    <node concave_ob="0" dyn_ob="0" id="2540008" lat="40.16026362" lon="116.11456643" smoke="0" type="-1" vel="4.2" water="0"/>
    <node concave_ob="0" dyn_ob="0" id="2540009" lat="40.16024700" lon="116.11455147" smoke="0" type="-1" vel="4.2" water="0">
        <tag k="highway" v="traffic_signals"/>
    </node>
    <way id="2540000">
        <nd ref="2490007"/>
        <nd ref="2540001"/>
        <nd ref="2540002"/>
        <nd ref="2540003"/>
        <nd ref="2540004"/>
        <nd ref="2540005"/>
        <nd ref="2540006"/>
        <nd ref="2540007"/>
        <nd ref="2540008"/>
        <nd ref="2540009"/>
        <tag k="name:en" v="double way"/>
    </way>
</osm>
