<?xml version="1.0" encoding="UTF-8"?>
<!--Generated by python, Author: Mengze.-->
<osm>
    <node concave_ob="0" dyn_ob="0" id="2130015" lat="40.15906747" lon="116.11647795" smoke="0" type="-1" vel="4.2" water="0">
        <tag k="highway" v="traffic_signals"/>
    </node>
    <node concave_ob="0" dyn_ob="0" id="2780002" lat="40.15900999" lon="116.11639260" smoke="0" type="-1" vel="4.2" water="0"/>
    <node concave_ob="0" dyn_ob="0" id="2780003" lat="40.15895904" lon="116.11628509" smoke="0" type="-1" vel="4.2" water="0"/>
    <node concave_ob="0" dyn_ob="0" id="2780004" lat="40.15892129" lon="116.11620348" smoke="0" type="-1" vel="8.4" water="0"/>
    <node concave_ob="0" dyn_ob="0" id="2780005" lat="40.15890395" lon="116.11613753" smoke="0" type="-1" vel="8.4" water="0"/>
    <node concave_ob="0" dyn_ob="0" id="2780006" lat="40.15886389" lon="116.11603614" smoke="0" type="-1" vel="8.4" water="0"/>
    <node concave_ob="0" dyn_ob="0" id="2780007" lat="40.15880529" lon="116.11595849" smoke="0" type="-1" vel="8.4" water="0"/>
    <node concave_ob="0" dyn_ob="0" id="2780008" lat="40.15875330" lon="116.11588913" smoke="0" type="-1" vel="8.4" water="0"/>
    <node concave_ob="0" dyn_ob="0" id="2780009" lat="40.15869918" lon="116.11582302" smoke="0" type="-1" vel="8.4" water="0"/>
    <node concave_ob="0" dyn_ob="0" id="2780010" lat="40.15864642" lon="116.11575840" smoke="0" type="-1" vel="8.4" water="0"/>
    <node concave_ob="0" dyn_ob="0" id="2780011" lat="40.15857643" lon="116.11568207" smoke="0" type="-1" vel="4.2" water="0"/>
    <node concave_ob="0" dyn_ob="0" id="2780012" lat="40.15854272" lon="116.11564797" smoke="0" type="-1" vel="4.2" water="0"/>
    <node concave_ob="0" dyn_ob="0" id="2770013" lat="40.15851122" lon="116.11560894" smoke="0" type="-1" vel="4.2" water="0">
        <tag k="highway" v="traffic_signals"/>
    </node>
    <way id="2780000">
        <nd ref="2130015"/>
        <nd ref="2780002"/>
        <nd ref="2780003"/>
        <nd ref="2780004"/>
        <nd ref="2780005"/>
        <nd ref="2780006"/>
        <nd ref="2780007"/>
        <nd ref="2780008"/>
        <nd ref="2780009"/>
        <nd ref="2780010"/>
        <nd ref="2780011"/>
        <nd ref="2780012"/>
        <nd ref="2770013"/>
        <tag k="name:en" v="double way"/>
    </way>
</osm>
