<?xml version="1.0" encoding="UTF-8"?>
<!--Generated by python, Author: Mengze.-->
<osm>
    <node concave_ob="0" dyn_ob="0" id="3620007" lat="40.15769084" lon="116.10800484" smoke="0" type="-1" vel="4.2" water="0">
        <tag k="highway" v="traffic_signals"/>
    </node>
    <node concave_ob="0" dyn_ob="0" id="4500001" lat="40.15763783" lon="116.10798897" smoke="0" type="-1" vel="4.2" water="0"/>
    <node concave_ob="0" dyn_ob="0" id="4500002" lat="40.15758486" lon="116.10796682" smoke="0" type="-1" vel="4.2" water="0"/>
    <node concave_ob="0" dyn_ob="0" id="4500003" lat="40.15751795" lon="116.10793901" smoke="0" type="-1" vel="8.4" water="0"/>
    <node concave_ob="0" dyn_ob="0" id="4500004" lat="40.15745277" lon="116.10791193" smoke="0" type="-1" vel="8.4" water="0"/>
    <node concave_ob="0" dyn_ob="0" id="4500005" lat="40.15740353" lon="116.10789133" smoke="0" type="-1" vel="8.4" water="0"/>
    <node concave_ob="0" dyn_ob="0" id="4500006" lat="40.15735679" lon="116.10787265" smoke="0" type="-1" vel="4.2" water="0"/>
    <node concave_ob="0" dyn_ob="0" id="4500007" lat="40.15731092" lon="116.10785431" smoke="0" type="-1" vel="4.2" water="0"/>
    <node concave_ob="0" dyn_ob="0" id="3580007" lat="40.15729261" lon="116.10783618" smoke="0" type="-1" vel="4.2" water="0">
        <tag k="highway" v="traffic_signals"/>
    </node>
    <way id="4500000">
        <nd ref="3620007"/>
        <nd ref="4500001"/>
        <nd ref="4500002"/>
        <nd ref="4500003"/>
        <nd ref="4500004"/>
        <nd ref="4500005"/>
        <nd ref="4500006"/>
        <nd ref="4500007"/>
        <nd ref="3580007"/>
        <tag k="name:en" v="double way"/>
    </way>
</osm>
