<?xml version="1.0" encoding="UTF-8"?>
<!--Generated by python, Author: Mengze.-->
<osm>
    <node concave_ob="0" dyn_ob="0" id="230006" lat="40.16974153" lon="116.12071066" smoke="0" type="-1" vel="4.2" water="0">
        <tag k="highway" v="traffic_signals"/>
    </node>
    <node concave_ob="0" dyn_ob="0" id="460002" lat="40.16961166" lon="116.12070373" smoke="0" type="-1" vel="4.2" water="0"/>
    <node concave_ob="0" dyn_ob="0" id="460003" lat="40.16953005" lon="116.12069531" smoke="0" type="-1" vel="4.2" water="0"/>
    <node concave_ob="0" dyn_ob="0" id="460004" lat="40.16944963" lon="116.12068701" smoke="0" type="-1" vel="8.4" water="0"/>
    <node concave_ob="0" dyn_ob="0" id="460005" lat="40.16937043" lon="116.12068384" smoke="0" type="-1" vel="4.2" water="0"/>
    <node concave_ob="0" dyn_ob="0" id="460006" lat="40.16929225" lon="116.12067077" smoke="0" type="-1" vel="4.2" water="0"/>
    <node concave_ob="0" dyn_ob="0" id="460007" lat="40.16921061" lon="116.12067344" smoke="0" type="-1" vel="4.2" water="0">
        <tag k="highway" v="traffic_signals"/>
    </node>
    <way id="460000">
        <nd ref="230006"/>
        <nd ref="460002"/>
        <nd ref="460003"/>
        <nd ref="460004"/>
        <nd ref="460005"/>
        <nd ref="460006"/>
        <nd ref="460007"/>
        <tag k="name:en" v="double way"/>
    </way>
</osm>
