<?xml version="1.0" encoding="UTF-8"?>
<!--Generated by python, Author: Mengze.-->
<osm>
    <node concave_ob="0" dyn_ob="0" id="3240064" lat="40.15561490" lon="116.10170812" smoke="0" type="-1" vel="4.2" water="0">
        <tag k="highway" v="traffic_signals"/>
    </node>
    <node concave_ob="0" dyn_ob="0" id="4800002" lat="40.15562569" lon="116.10173963" smoke="0" type="-1" vel="4.2" water="0"/>
    <node concave_ob="0" dyn_ob="0" id="4800003" lat="40.15566737" lon="116.10177743" smoke="0" type="-1" vel="4.2" water="0"/>
    <node concave_ob="0" dyn_ob="0" id="4800004" lat="40.15574412" lon="116.10179095" smoke="0" type="-1" vel="8.4" water="0"/>
    <node concave_ob="0" dyn_ob="0" id="4800005" lat="40.15581968" lon="116.10178896" smoke="0" type="-1" vel="8.4" water="0"/>
    <node concave_ob="0" dyn_ob="0" id="4800006" lat="40.15588183" lon="116.10180169" smoke="0" type="-1" vel="8.4" water="0"/>
    <node concave_ob="0" dyn_ob="0" id="4800007" lat="40.15595703" lon="116.10183007" smoke="0" type="-1" vel="8.4" water="0"/>
    <node concave_ob="0" dyn_ob="0" id="4800008" lat="40.15600886" lon="116.10190245" smoke="0" type="-1" vel="8.4" water="0"/>
    <node concave_ob="0" dyn_ob="0" id="4800009" lat="40.15604255" lon="116.10197238" smoke="0" type="-1" vel="8.4" water="0"/>
    <node concave_ob="0" dyn_ob="0" id="4800010" lat="40.15607814" lon="116.10204187" smoke="0" type="-1" vel="8.4" water="0"/>
    <node concave_ob="0" dyn_ob="0" id="4800011" lat="40.15610601" lon="116.10208042" smoke="0" type="-1" vel="8.4" water="0"/>
    <node concave_ob="0" dyn_ob="0" id="4800012" lat="40.15613840" lon="116.10211254" smoke="0" type="-1" vel="8.4" water="0"/>
    <node concave_ob="0" dyn_ob="0" id="4800013" lat="40.15619264" lon="116.10213846" smoke="0" type="-1" vel="4.2" water="0"/>
    <node concave_ob="0" dyn_ob="0" id="4800014" lat="40.15623818" lon="116.10214476" smoke="0" type="-1" vel="4.2" water="0"/>
    <node concave_ob="0" dyn_ob="0" id="4800015" lat="40.15628057" lon="116.10214172" smoke="0" type="-1" vel="4.2" water="0">
        <tag k="highway" v="traffic_signals"/>
    </node>
    <way id="4800000">
        <nd ref="3240064"/>
        <nd ref="4800002"/>
        <nd ref="4800003"/>
        <nd ref="4800004"/>
        <nd ref="4800005"/>
        <nd ref="4800006"/>
        <nd ref="4800007"/>
        <nd ref="4800008"/>
        <nd ref="4800009"/>
        <nd ref="4800010"/>
        <nd ref="4800011"/>
        <nd ref="4800012"/>
        <nd ref="4800013"/>
        <nd ref="4800014"/>
        <nd ref="4800015"/>
        <tag k="name:en" v="double way"/>
    </way>
</osm>
