<?xml version="1.0" encoding="UTF-8"?>
<!--Generated by python, Author: Mengze.-->
<osm>
    <node concave_ob="0" dyn_ob="0" id="5700006" lat="40.16018868" lon="116.09448991" smoke="0" type="-1" vel="4.2" water="0">
        <tag k="highway" v="traffic_signals"/>
    </node>
    <node concave_ob="0" dyn_ob="0" id="5710002" lat="40.16023726" lon="116.09449878" smoke="0" type="-1" vel="4.2" water="0"/>
    <node concave_ob="0" dyn_ob="0" id="5710003" lat="40.16031242" lon="116.09450400" smoke="0" type="-1" vel="4.2" water="0"/>
    <node concave_ob="0" dyn_ob="0" id="5710004" lat="40.16035949" lon="116.09451349" smoke="0" type="-1" vel="8.4" water="0"/>
    <node concave_ob="0" dyn_ob="0" id="5710005" lat="40.16040996" lon="116.09451942" smoke="0" type="-1" vel="8.4" water="0"/>
    <node concave_ob="0" dyn_ob="0" id="5710006" lat="40.16048527" lon="116.09452864" smoke="0" type="-1" vel="4.2" water="0"/>
    <node concave_ob="0" dyn_ob="0" id="5710007" lat="40.16053682" lon="116.09453492" smoke="0" type="-1" vel="4.2" water="0"/>
    <node concave_ob="0" dyn_ob="0" id="5710008" lat="40.16056091" lon="116.09454184" smoke="0" type="-1" vel="4.2" water="0">
        <tag k="highway" v="traffic_signals"/>
    </node>
    <way id="5710000">
        <nd ref="5700006"/>
        <nd ref="5710002"/>
        <nd ref="5710003"/>
        <nd ref="5710004"/>
        <nd ref="5710005"/>
        <nd ref="5710006"/>
        <nd ref="5710007"/>
        <nd ref="5710008"/>
        <tag k="name:en" v="double way"/>
    </way>
</osm>
