<?xml version="1.0" encoding="UTF-8"?>
<!--Generated by python, Author: Mengze.-->
<osm>
    <node concave_ob="0" dyn_ob="0" id="5730004" lat="40.16077312" lon="116.09457021" smoke="0" type="-1" vel="4.2" water="0">
        <tag k="highway" v="traffic_signals"/>
    </node>
    <node concave_ob="0" dyn_ob="0" id="5740001" lat="40.16071039" lon="116.09456010" smoke="0" type="-1" vel="4.2" water="0"/>
    <node concave_ob="0" dyn_ob="0" id="5740002" lat="40.16068565" lon="116.09455640" smoke="0" type="-1" vel="4.2" water="0"/>
    <node concave_ob="0" dyn_ob="0" id="5740003" lat="40.16063655" lon="116.09454904" smoke="0" type="-1" vel="4.2" water="0"/>
    <node concave_ob="0" dyn_ob="0" id="5740004" lat="40.16061218" lon="116.09454539" smoke="0" type="-1" vel="4.2" water="0"/>
    <node concave_ob="0" dyn_ob="0" id="5710008" lat="40.16056091" lon="116.09454184" smoke="0" type="-1" vel="4.2" water="0">
        <tag k="highway" v="traffic_signals"/>
    </node>
    <way id="5740000">
        <nd ref="5730004"/>
        <nd ref="5740001"/>
        <nd ref="5740002"/>
        <nd ref="5740003"/>
        <nd ref="5740004"/>
        <nd ref="5710008"/>
        <tag k="name:en" v="double way"/>
    </way>
</osm>
