<?xml version="1.0" encoding="UTF-8"?>
<!--Generated by python, Author: Mengze.-->
<osm>
    <node concave_ob="0" dyn_ob="0" id="110011" lat="39.82310688" lon="116.18320264" smoke="0" type="3" vel="4.2" water="0">
        <tag k="highway" v="traffic_signals"/>
    </node>
    <node concave_ob="0" dyn_ob="0" id="180001" lat="39.82311925" lon="116.18323207" smoke="0" type="-1" vel="4.2" water="0"/>
    <node concave_ob="0" dyn_ob="0" id="180002" lat="39.82315084" lon="116.18328781" smoke="0" type="-1" vel="4.2" water="0"/>
    <node concave_ob="0" dyn_ob="0" id="180003" lat="39.82317289" lon="116.18334220" smoke="0" type="-1" vel="8.4" water="0"/>
    <node concave_ob="0" dyn_ob="0" id="180004" lat="39.82319298" lon="116.18337999" smoke="0" type="-1" vel="8.4" water="0"/>
    <node concave_ob="0" dyn_ob="0" id="180005" lat="39.82320605" lon="116.18339959" smoke="0" type="-1" vel="8.4" water="0"/>
    <node concave_ob="0" dyn_ob="0" id="180006" lat="39.82321339" lon="116.18341490" smoke="0" type="-1" vel="8.4" water="0"/>
    <node concave_ob="0" dyn_ob="0" id="180007" lat="39.82322574" lon="116.18343719" smoke="0" type="-1" vel="8.4" water="0"/>
    <node concave_ob="0" dyn_ob="0" id="180008" lat="39.82323232" lon="116.18345283" smoke="0" type="-1" vel="8.4" water="0"/>
    <node concave_ob="0" dyn_ob="0" id="180009" lat="39.82323560" lon="116.18346124" smoke="0" type="-1" vel="8.4" water="0"/>
    <node concave_ob="0" dyn_ob="0" id="180010" lat="39.82324973" lon="116.18349150" smoke="0" type="-1" vel="8.4" water="0"/>
    <node concave_ob="0" dyn_ob="0" id="180011" lat="39.82326486" lon="116.18352189" smoke="0" type="-1" vel="8.4" water="0"/>
    <node concave_ob="0" dyn_ob="0" id="180012" lat="39.82327583" lon="116.18354635" smoke="0" type="-1" vel="8.4" water="0"/>
    <node concave_ob="0" dyn_ob="0" id="180013" lat="39.82328170" lon="116.18356370" smoke="0" type="-1" vel="8.4" water="0"/>
    <node concave_ob="0" dyn_ob="0" id="180014" lat="39.82329276" lon="116.18358956" smoke="0" type="-1" vel="8.4" water="0"/>
    <node concave_ob="0" dyn_ob="0" id="180015" lat="39.82330139" lon="116.18360561" smoke="0" type="-1" vel="8.4" water="0"/>
    <node concave_ob="0" dyn_ob="0" id="180016" lat="39.82330824" lon="116.18362308" smoke="0" type="-1" vel="8.4" water="0"/>
    <node concave_ob="0" dyn_ob="0" id="180017" lat="39.82331675" lon="116.18364961" smoke="0" type="-1" vel="8.4" water="0"/>
    <node concave_ob="0" dyn_ob="0" id="180018" lat="39.82332438" lon="116.18367633" smoke="0" type="-1" vel="8.4" water="0"/>
    <node concave_ob="0" dyn_ob="0" id="180019" lat="39.82333461" lon="116.18371212" smoke="0" type="-1" vel="8.4" water="0"/>
    <node concave_ob="0" dyn_ob="0" id="180020" lat="39.82333977" lon="116.18372894" smoke="0" type="-1" vel="8.4" water="0"/>
    <node concave_ob="0" dyn_ob="0" id="180021" lat="39.82335361" lon="116.18377284" smoke="0" type="-1" vel="8.4" water="0"/>
    <node concave_ob="0" dyn_ob="0" id="180022" lat="39.82336139" lon="116.18380005" smoke="0" type="-1" vel="8.4" water="0"/>
    <node concave_ob="0" dyn_ob="0" id="180023" lat="39.82336826" lon="116.18382739" smoke="0" type="-1" vel="8.4" water="0"/>
    <node concave_ob="0" dyn_ob="0" id="180024" lat="39.82337244" lon="116.18385601" smoke="0" type="-1" vel="8.4" water="0"/>
    <node concave_ob="0" dyn_ob="0" id="180025" lat="39.82337837" lon="116.18388462" smoke="0" type="-1" vel="8.4" water="0"/>
    <node concave_ob="0" dyn_ob="0" id="180026" lat="39.82338059" lon="116.18391223" smoke="0" type="-1" vel="8.4" water="0"/>
    <node concave_ob="0" dyn_ob="0" id="180027" lat="39.82338286" lon="116.18394222" smoke="0" type="-1" vel="8.4" water="0"/>
    <node concave_ob="0" dyn_ob="0" id="180028" lat="39.82338406" lon="116.18396303" smoke="0" type="-1" vel="8.4" water="0"/>
    <node concave_ob="0" dyn_ob="0" id="180029" lat="39.82338718" lon="116.18398161" smoke="0" type="-1" vel="8.4" water="0"/>
    <node concave_ob="0" dyn_ob="0" id="180030" lat="39.82338839" lon="116.18400250" smoke="0" type="-1" vel="8.4" water="0"/>
    <node concave_ob="0" dyn_ob="0" id="180031" lat="39.82338863" lon="116.18402338" smoke="0" type="-1" vel="8.4" water="0"/>
    <node concave_ob="0" dyn_ob="0" id="180032" lat="39.82338651" lon="116.18405559" smoke="0" type="-1" vel="8.4" water="0"/>
    <node concave_ob="0" dyn_ob="0" id="180033" lat="39.82338459" lon="116.18408395" smoke="0" type="-1" vel="8.4" water="0"/>
    <node concave_ob="0" dyn_ob="0" id="180034" lat="39.82338257" lon="116.18409980" smoke="0" type="-1" vel="8.4" water="0"/>
    <node concave_ob="0" dyn_ob="0" id="180035" lat="39.82338126" lon="116.18411452" smoke="0" type="-1" vel="8.4" water="0"/>
    <node concave_ob="0" dyn_ob="0" id="180036" lat="39.82338004" lon="116.18413905" smoke="0" type="-1" vel="8.4" water="0"/>
    <node concave_ob="0" dyn_ob="0" id="180037" lat="39.82337804" lon="116.18415391" smoke="0" type="-1" vel="4.2" water="0"/>
    <node concave_ob="0" dyn_ob="0" id="180038" lat="39.82337535" lon="116.18416891" smoke="0" type="-1" vel="4.2" water="0"/>
    <node concave_ob="0" dyn_ob="0" id="180039" lat="39.82337273" lon="116.18419191" smoke="0" type="3" vel="4.2" water="0">
        <tag k="highway" v="traffic_signals"/>
    </node>
    <way id="180000">
        <nd ref="110011"/>
        <nd ref="180001"/>
        <nd ref="180002"/>
        <nd ref="180003"/>
        <nd ref="180004"/>
        <nd ref="180005"/>
        <nd ref="180006"/>
        <nd ref="180007"/>
        <nd ref="180008"/>
        <nd ref="180009"/>
        <nd ref="180010"/>
        <nd ref="180011"/>
        <nd ref="180012"/>
        <nd ref="180013"/>
        <nd ref="180014"/>
        <nd ref="180015"/>
        <nd ref="180016"/>
        <nd ref="180017"/>
        <nd ref="180018"/>
        <nd ref="180019"/>
        <nd ref="180020"/>
        <nd ref="180021"/>
        <nd ref="180022"/>
        <nd ref="180023"/>
        <nd ref="180024"/>
        <nd ref="180025"/>
        <nd ref="180026"/>
        <nd ref="180027"/>
        <nd ref="180028"/>
        <nd ref="180029"/>
        <nd ref="180030"/>
        <nd ref="180031"/>
        <nd ref="180032"/>
        <nd ref="180033"/>
        <nd ref="180034"/>
        <nd ref="180035"/>
        <nd ref="180036"/>
        <nd ref="180037"/>
        <nd ref="180038"/>
        <nd ref="180039"/>
        <tag k="name:en" v="double way"/>
    </way>
</osm>
